{
	"files":[
		{
			"classes":[
				"view",
				"viewTrait"
			],
			"file":"libraries/mvc/view.php"
		},
		{
			"classes":["controller"],
			"file":"libraries/mvc/controller.php"
		},
		{
			"classes":["views\\listview"],
			"file":"libraries/mvc/views/list.php"
		},
		{
			"classes":["views\\error"],
			"file":"libraries/mvc/views/error.php"
		},
		{
			"classes":["views\\form"],
			"file":"libraries/mvc/views/form.php"
		},
		{
			"classes":["authorization"],
			"file":"libraries/users/authorization.php"
		},
		{
			"classes":["authentication"],
			"file":"libraries/users/authentication.php"
		},
		{
			"classes":["log"],
			"file":"libraries/logging/logs.php"
		},
		{
			"classes":["controllers\\ticketing"],
			"file":"controllers/ticketing.php"
		},
		{
			"classes":["controllers\\settings\\departments"],
			"file":"controllers/settings/departments.php"
		},
		{
			"classes":["ticket"],
			"file":"libraries/ticketing/tickets.php"
		},
		{
			"classes":["Parsedown"],
			"file":"libraries/markdown/Parsedown.php"
		},
		{
			"classes":["ticket_message"],
			"file":"libraries/ticketing/ticket.msg.php"
		},
		{
			"classes":["department"],
			"file":"libraries/ticketing/department.php"
		},
		{
			"classes":["ticket_param"],
			"file":"libraries/ticketing/tickets.params.php"
		},
		{
			"classes":["ticket_file"],
			"file":"libraries/ticketing/tickets.files.php"
		},
		{
			"classes":["views\\ticketlist"],
			"file":"views/ticketing/list.php"
		},
		{
			"classes":["views\\add"],
			"file":"views/ticketing/add.php"
		},
		{
			"classes":["views\\view"],
			"file":"views/ticketing/view.php"
		},
		{
			"classes":["views\\edit"],
			"file":"views/ticketing/edit.php"
		},
		{
			"classes":["views\\lock"],
			"file":"views/ticketing/lock.php"
		},
		{
			"classes":["views\\unlock"],
			"file":"views/ticketing/unlock.php"
		},
		{
			"classes":["views\\delete"],
			"file":"views/ticketing/delete.php"
		},
		{
			"classes":["views\\message_delete"],
			"file":"views/ticketing/message.delete.php"
		},
		{
			"classes":["views\\message_edit"],
			"file":"views/ticketing/message.edit.php"
		},
		{
			"classes":["events\\product_list"],
			"file":"libraries/events/product_list.php"
		},
		{
			"classes":["product"],
			"file":"libraries/products/product.php"
		},
		{
			"classes":["service"],
			"file":"libraries/products/service.php"
		},
		{
			"classes":["products"],
			"file":"libraries/products/products.php"
		},
		{
			"classes":["listeners\\settings\\usertype"],
			"file":"listeners/settings/usertype.php"
		},
		{
			"classes":["views\\settings\\department\\listview"],
			"file":"views/settings/department/list.php"
		},
		{
			"classes":["views\\settings\\department\\delete"],
			"file":"views/settings/department/delete.php"
		},
		{
			"classes":["views\\settings\\department\\add"],
			"file":"views/settings/department/add.php"
		},
		{
			"classes":["views\\settings\\department\\edit"],
			"file":"views/settings/department/edit.php"
		}
	]
}
